{
  "name": "hexparty.entry.socket_patterns",
  "category": "hexcasting:patterns",
  "icon": "hexparty:impetus/socket",
  "sortnum": 25,
  "advancement": "hexcasting:enlightenment",
  "entry_color": "54398a",
  "pages": [
    {
      "type": "patchouli:text",
      "text": "hexparty.page.socket_patterns.entry"
    },
    {
      "type": "hexcasting:brainsweep",
      "recipe": "hexparty:brainsweep/impetus_socket",
      "text": "hexparty.page.brainsweeping.impetus_socket"
    },
    {
      "type": "patchouli:text",
      "text": "hexparty.page.socket_patterns.usage"
    },
    {
      "type": "hexcasting:pattern",
      "op_id": "hexparty:read",
      "anchor": "hexparty:read",
      "input": "",
      "output": "str",
      "text": "hexparty.page.socket_patterns.read"
    },
    {
      "type": "hexcasting:pattern",
      "op_id": "hexparty:get_host",
      "anchor": "hexparty:get_host",
      "input": "vec",
      "output": "str | null",
      "text": "hexparty.page.socket_patterns.get_host"
    },
    {
      "type": "hexcasting:pattern",
      "op_id": "hexparty:get_port",
      "anchor": "hexparty:get_port",
      "input": "vec",
      "output": "int",
      "text": "hexparty.page.socket_patterns.get_port"
    }
  ]
}